emoji/__init__.py
emoji/cli.py
emoji/emoji.py
emoji2-0.2.1.dist-info/AUTHORS.rst
emoji2-0.2.1.dist-info/LICENSE
emoji2-0.2.1.dist-info/METADATA
emoji2-0.2.1.dist-info/WHEEL
emoji2-0.2.1.dist-info/entry_points.txt
emoji2-0.2.1.dist-info/top_level.txt
emoji2-0.2.1.dist-info/RECORD
