Metadata-Version: 2.1
Name: emoji2
Version: 0.2.1
Summary: Search emoji by keywords in terminal.
Home-page: https://github.com/lonsty/emoji
Author: Allen Shaw
Author-email: lonsty@sina.com
License: MIT license
Keywords: emoji
Platform: UNKNOWN
Classifier: Development Status :: 2 - Pre-Alpha
Classifier: Intended Audience :: Developers
Classifier: License :: OSI Approved :: MIT License
Classifier: Natural Language :: English
Classifier: Programming Language :: Python :: 3
Classifier: Programming Language :: Python :: 3.6
Classifier: Programming Language :: Python :: 3.7
Classifier: Programming Language :: Python :: 3.8
Requires-Python: >=3.6
Requires-Dist: Click (>=7.0)
Requires-Dist: requests (>=2.23.0)
Requires-Dist: beautifulsoup4 (>=4.9.1)
